nshconfig/__init__.py
nshconfig/_src/adapter.py
nshconfig/_src/config.py
nshconfig/_src/export.py
nshconfig/_src/invalid.py
nshconfig/_src/json_schema.py
nshconfig/_src/missing.py
nshconfig/_src/pydantic_exports.py
nshconfig/_src/registry.py
nshconfig/_src/singleton.py
nshconfig/_src/treescope_util.py
nshconfig/_src/typing_inspect_.py
nshconfig/_src/utils.py
nshconfig/bin/export.py
nshconfig-0.53.1.dist-info/WHEEL
nshconfig-0.53.1.dist-info/entry_points.txt
nshconfig-0.53.1.dist-info/METADATA
nshconfig-0.53.1.dist-info/RECORD
