Metadata-Version: 2.3
Name: nshconfig
Version: 0.53.1
Summary: Fully typed configuration management, powered by Pydantic
Author: Nima Shoghi
Author-email: Nima Shoghi <nimashoghi@gmail.com>
Requires-Dist: pydantic>=2
Requires-Dist: typing-extensions
Requires-Dist: eval-type-backport ; python_full_version < '3.10'
Requires-Dist: treescope ; python_full_version >= '3.10' and extra == 'all'
Requires-Dist: pydantic-yaml ; extra == 'all'
Requires-Dist: tomli ; extra == 'all'
Requires-Dist: tomli-w ; extra == 'all'
Requires-Dist: sphinx ; extra == 'docs'
Requires-Dist: sphinx-rtd-theme ; extra == 'docs'
Requires-Dist: myst-parser ; extra == 'docs'
Requires-Dist: sphinx-copybutton ; extra == 'docs'
Requires-Dist: treescope ; python_full_version >= '3.10' and extra == 'extra'
Requires-Dist: pydantic-yaml ; extra == 'extra'
Requires-Dist: tomli ; extra == 'extra'
Requires-Dist: tomli-w ; extra == 'extra'
Requires-Dist: tomli ; extra == 'toml'
Requires-Dist: tomli-w ; extra == 'toml'
Requires-Dist: pydantic-yaml ; extra == 'yaml'
Requires-Python: >=3.9, <4.0
Project-URL: homepage, https://github.com/nimashoghi/nshconfig
Provides-Extra: all
Provides-Extra: docs
Provides-Extra: extra
Provides-Extra: toml
Provides-Extra: yaml
